prompt_spec/__init__.py
prompt_spec/cli.py
prompt_spec/core/__init__.py
prompt_spec/core/load_prompt.py
prompt_spec/core/populate_prompt.py
prompt_spec/core/prompt_template.py
prompt_spec/core/utils.py
prompt_spec-0.1.4.dist-info/licenses/LICENSE
prompt_spec-0.1.4.dist-info/METADATA
prompt_spec-0.1.4.dist-info/WHEEL
prompt_spec-0.1.4.dist-info/entry_points.txt
prompt_spec-0.1.4.dist-info/top_level.txt
prompt_spec-0.1.4.dist-info/RECORD
