Metadata-Version: 2.4
Name: prompt-spec
Version: 0.1.4
Summary: Lightweight pydantic wrapper prompting library to support sharing of oncology-related LLM prompts
Requires-Python: >=3.11
License-File: LICENSE
Requires-Dist: linkml>=1.9.5
Requires-Dist: linkml-runtime>=1.9.5
Requires-Dist: openai>=2.8.0
Requires-Dist: pydantic>=2.12.4
Requires-Dist: python-dotenv>=1.2.1
Requires-Dist: ruamel-yaml>=0.18.16
Requires-Dist: typer>=0.20.0
Dynamic: license-file
